{"place": {"場所類型": "高中職", "場所網址": "http://www.mhvs.cyc.edu.tw/newpage/frameMain.htm", "場所地址": "嘉義縣民雄鄉文隆村81號", "場所描述": "國立民雄農工校門進來直走到圓環上右側斜坡直走到忠孝樓健康中心1樓", "場所名稱": "國立民雄高級農工職業學校", "場所經緯度": {"y": 23.538435, "x": 120.426464}}, "aed": {"開放使用時間": "星期一至星期五 06:30 至 18:00\n                星期六 06:30 至 18:00\n                星期日 06:30 至 18:00\n                備註:開放使用時間如上述時段提供大眾使用", "AED放置地點": "健康中心門口旁三公尺臨近中走廊", "AED經緯度": {"y": 23.538435, "x": 120.426464}, "開放使用時間緊急連絡電話": "05-2267120", "AED地點描述": "忠孝樓健康中心門口旁三公尺臨近中走廊", "資料建立時間": "2013-12-16 16:14:00.0"}}