{"aed": {"開放使用時間緊急連絡電話": "5222492*2042", "AED地點描述": "警衛室牆壁上", "AED放置地點": "警衛室內", "開放使用時間": "星期一至星期五 07:00 至 21:00\n                星期六 07:00 至 21:00\n                星期日 07:00 至 07:00\n                備註:", "資料建立時間": "2014-05-14 10:48:00.0", "AED經緯度": {"y": 24.802645, "x": 120.959967}}, "place": {"場所經緯度": {"y": 24.802645, "x": 120.959967}, "場所網址": "http://http://www.cmps.hc.edu.tw/", "場所描述": "本校於民國四十一年八月一日奉准創立，以崇禮里、南勢里、曲溪里、客雅里、西雅里、福德里、育英里、興南里、台溪里等為學區，定名新竹縣新竹市西門國民小學，新竹市升格後改名為新竹市北區西門國民小學、本校位於北大路與延平路交會處。", "場所類型": "國小", "場所名稱": "新竹市北區西門國小", "場所地址": "新竹市北區北大路450號"}}