{"aed": {"開放使用時間緊急連絡電話": "02-29332199分機101", "AED地點描述": "放置於本處文山劇場一樓大廳休息區，為室內開放空間，利於設備維護，大樓鄰近景美捷運站一號出口及羅斯福路六段，方便支援。", "AED放置地點": "文山劇場一樓大廳休息區", "開放使用時間": "星期一至星期五 09:00 至 17:00\n                星期六 09:00 至 17:00\n                星期日 09:00 至 17:00\n                備註:星期一、春節、端午節、中秋節及選舉日休館。", "資料建立時間": "2014-05-28 12:43:00.0", "AED經緯度": {"y": 24.991961, "x": 121.541233}}, "place": {"場所經緯度": {"y": 24.991961, "x": 121.541233}, "場所網址": "http://www.tmseh.taipei.gov.tw", "場所描述": "", "場所類型": "其他場所", "場所名稱": "臺北市藝文推廣處-文山劇場", "場所地址": "台北市文山區景文街32號"}}