{"place": {"場所類型": "文化園區", "場所網址": "http://www.gep.ntpc.gov.tw/", "場所地址": "新北市瑞芳區金光路8號", "場所描述": "本館位於金瓜石山城內，將金瓜石地區珍貴的自然景觀特色、歷史記憶及人文資產做完整的保存，並企圖賦予新的生命。", "場所名稱": "新北市立黃金博物館", "場所經緯度": {"y": 25.108349, "x": 121.856252}}, "aed": {"開放使用時間": "星期一至星期五 09:30 至 17:00\n                星期六 09:30 至 18:00\n                星期日 09:30 至 18:00\n                備註:休館日為每月第1個星期一（預國定假日順延一天）、農曆除夕、年初一、選舉日，其他必要之休館日將另行公告。", "AED放置地點": "本山五坑", "AED經緯度": {"y": 25.108349, "x": 121.856252}, "開放使用時間緊急連絡電話": "（02）24962800＃2892", "AED地點描述": "體驗坑道入口", "資料建立時間": "2013-10-17 09:02:00.0"}}