{"place": {"場所類型": "直轄市、縣(市)政府主管之風景區", "場所網址": "http://kcs.kcg.gov.tw/", "場所地址": "高雄市前金區中正四路211號5樓之3", "場所描述": "新光碼頭 21號碼頭", "場所名稱": "高雄市輪船(股)公司  新光碼頭站", "場所經緯度": {"y": 22.609326, "x": 120.297198}}, "aed": {"開放使用時間": "星期一至星期五 16:00 至 21:00\n                星期六 16:00 至 21:00\n                星期日 16:00 至 21:00\n                備註:", "AED放置地點": "高雄市輪船(股)公司  新光碼頭站", "AED經緯度": {"y": 22.609326, "x": 120.297198}, "開放使用時間緊急連絡電話": "3220998", "AED地點描述": "大門進入後，左側靠牆處，(因本站體內為開放空間，無任何遮蔽物，進入後，即可清楚看見AED擺放位置)。", "資料建立時間": "2014-10-07 09:54:00.0"}}