{"aed": {"開放使用時間緊急連絡電話": "00:00-23:55", "AED地點描述": "一樓大廳電梯門口前方", "AED放置地點": "一樓大廳", "開放使用時間": "星期一至星期五 00:00 至 00:00\n                星期六 00:00 至 00:00\n                星期日 00:00 至 00:00\n                備註:", "資料建立時間": "2015-01-28 15:20:00.0", "AED經緯度": {"y": 23.563866, "x": 119.567601}}, "place": {"場所經緯度": {"y": 23.563866, "x": 119.567601}, "場所網址": "http://www.festival.com.tw", "場所描述": "優美的海岸線，進出漁港的船隻，等待豐收的人群，佇立漁港的海鳥，耀眼奪目的陽光，飛舞的海風，嘉華大飯店就是位於漁人碼頭旁，這樣充滿生命力的地方。\r嘉華大飯店擁有旅居生活中最佳的居住品質，距機場約15分鐘車程，備有專車接機服務，有最寬敞精緻的商務套房；從高處可俯瞰整個漁人碼頭的美景，觀賞漁港內的繁星點點漁燈，絕佳的居住視野，讓您隨時可以將美麗的海岸風景拉入室內，享受整個旅程的浪漫氣息，滿心洋溢幸福的滋味，讓人忘卻時光流逝的痕跡。", "場所類型": "飯店", "場所名稱": "和益顧問有限公司(嘉華大飯店)", "場所地址": "澎湖縣馬公市民福路6號"}}